anemoi/plugins/ecmwf/inference/__init__.py
anemoi/plugins/ecmwf/inference/_version.py
anemoi/plugins/ecmwf/inference/dynamics/README.md
anemoi/plugins/ecmwf/inference/dynamics/__init__.py
anemoi/plugins/ecmwf/inference/dynamics/_operate_on_fields.py
anemoi/plugins/ecmwf/inference/dynamics/array_overlay.py
anemoi/plugins/ecmwf/inference/dynamics/modify_value.py
anemoi/plugins/ecmwf/inference/mir_templates/README.md
anemoi/plugins/ecmwf/inference/mir_templates/__init__.py
anemoi/plugins/ecmwf/inference/mir_templates/base_handles.yaml
anemoi/plugins/ecmwf/inference/mir_templates/mir_templates.py
anemoi/plugins/ecmwf/inference/multio/README.md
anemoi/plugins/ecmwf/inference/multio/__init__.py
anemoi/plugins/ecmwf/inference/multio/archive.py
anemoi/plugins/ecmwf/inference/multio/multio_output.py
anemoi/plugins/ecmwf/inference/multio/plans/README.md
anemoi/plugins/ecmwf/inference/multio/plans/debug.yaml
anemoi/plugins/ecmwf/inference/multio/plans/to_fdb.yaml
anemoi/plugins/ecmwf/inference/multio/plans/to_file.yaml
anemoi/plugins/ecmwf/inference/opendata/README.md
anemoi/plugins/ecmwf/inference/opendata/__init__.py
anemoi/plugins/ecmwf/inference/opendata/geopotential_height.py
anemoi/plugins/ecmwf/inference/opendata/mappings.yaml
anemoi/plugins/ecmwf/inference/opendata/opendata.py
anemoi/plugins/ecmwf/inference/polytope/README.md
anemoi/plugins/ecmwf/inference/polytope/__init__.py
anemoi/plugins/ecmwf/inference/polytope/polytope.py
anemoi/plugins/ecmwf/inference/regrid/README.md
anemoi/plugins/ecmwf/inference/regrid/__init__.py
anemoi/plugins/ecmwf/inference/regrid/regrid.py
anemoi_plugins_ecmwf_inference-0.1.21.dist-info/licenses/LICENSE
anemoi_plugins_ecmwf_inference-0.1.21.dist-info/METADATA
anemoi_plugins_ecmwf_inference-0.1.21.dist-info/WHEEL
anemoi_plugins_ecmwf_inference-0.1.21.dist-info/entry_points.txt
anemoi_plugins_ecmwf_inference-0.1.21.dist-info/top_level.txt
anemoi_plugins_ecmwf_inference-0.1.21.dist-info/RECORD
