Metadata-Version: 2.4
Name: anemoi-plugins-ecmwf-inference
Version: 0.1.21
Summary: Plugins for anemoi.inference as built by ECMWF
Author-email: "European Centre for Medium-Range Weather Forecasts (ECMWF)" <software.support@ecmwf.int>
License:                                  Apache License
Project-URL: Homepage, https://github.com/ecmwf/anemoi-plugins-ecmwf
Keywords: anemoi-inference
Classifier: Development Status :: 3 - Alpha
Classifier: Operating System :: OS Independent
Classifier: Programming Language :: Python :: 3 :: Only
Classifier: Programming Language :: Python :: 3.10
Classifier: Programming Language :: Python :: 3.11
Classifier: Programming Language :: Python :: 3.12
Classifier: Programming Language :: Python :: 3.13
Classifier: Programming Language :: Python :: Implementation :: CPython
Classifier: Programming Language :: Python :: Implementation :: PyPy
Requires-Python: >=3.10
License-File: LICENSE
Requires-Dist: anemoi-inference>=0.8.1
Provides-Extra: all
Requires-Dist: anemoi-plugins-ecmwf-inference[mir,multio,opendata,polytope]; extra == "all"
Provides-Extra: dynamics
Requires-Dist: earthkit-regrid; extra == "dynamics"
Requires-Dist: pillow; extra == "dynamics"
Provides-Extra: mir
Requires-Dist: earthkit-data; extra == "mir"
Requires-Dist: mir-python>=1.27.10.5; extra == "mir"
Provides-Extra: multio
Requires-Dist: pymultio[all]>=2.7.1.5; extra == "multio"
Provides-Extra: opendata
Requires-Dist: anemoi-plugins-ecmwf-inference[regrid]; extra == "opendata"
Requires-Dist: earthkit-data; extra == "opendata"
Requires-Dist: earthkit-regrid; extra == "opendata"
Requires-Dist: ecmwf-opendata; extra == "opendata"
Provides-Extra: polytope
Requires-Dist: earthkit-data[polytope]; extra == "polytope"
Provides-Extra: regrid
Requires-Dist: anemoi-plugins-ecmwf-inference[mir]; extra == "regrid"
Provides-Extra: tests
Requires-Dist: anemoi-plugins-ecmwf-inference[all]; extra == "tests"
Requires-Dist: pytest; extra == "tests"
Requires-Dist: pytest-mock; extra == "tests"
Requires-Dist: pytest-xdist; extra == "tests"
Dynamic: license-file
